dictshaper/__init__.py
dictshaper/shaper.py
dictshaper-0.0.4.dist-info/METADATA
dictshaper-0.0.4.dist-info/WHEEL
dictshaper-0.0.4.dist-info/licenses/LICENSE
dictshaper-0.0.4.dist-info/RECORD
