Metadata-Version: 2.1
Name: dictshaper
Version: 0.0.4
Summary: Form a dictionary to a convenient shape for output or writing to a file.
Project-URL: Homepage, https://github.com/Belingood/dictshaper
Project-URL: Bug Tracker, https://github.com/Belingood/dictshaper/issues
Author-email: Belingood <sampasabie@tutanota.com>
License-File: LICENSE
Classifier: License :: OSI Approved :: MIT License
Classifier: Operating System :: OS Independent
Classifier: Programming Language :: Python :: 3
Requires-Python: >=3.7
